piopiy/__init__.py
piopiy/action/__init__.py
piopiy/action/action.py
piopiy/action/bridge.py
piopiy/action/input.py
piopiy/action/play_stream.py
piopiy/action/stream.py
piopiy/action/stream_action.py
piopiy/underscore/__init__.py
piopiy/underscore/underscore.py
piopiy/voice/__init__.py
piopiy/voice/ai_agent.py
piopiy/voice/client.py
piopiy/voice/hangup.py
piopiy/voice/hold.py
piopiy/voice/pcmo_call.py
piopiy/voice/voice.py
piopiy-1.1.0.dist-info/LICENSE.txt
piopiy-1.1.0.dist-info/METADATA
piopiy-1.1.0.dist-info/WHEEL
piopiy-1.1.0.dist-info/top_level.txt
piopiy-1.1.0.dist-info/RECORD
