Metadata-Version: 2.1
Name: piopiy
Version: 1.1.0
Summary: PIOPIY: Complete Voice AI Agent & CPaaS Platform SDK (Voice, Queue, Campaigns, WhatsApp, SMS)
Home-page: https://github.com/telecmi/piopiy_python
Author: PIOPIY
Author-email: support@telecmi.com
License: Apache 2.0
Platform: any
Classifier: Programming Language :: Python
Classifier: License :: OSI Approved :: Apache Software License
Classifier: Programming Language :: Python :: 3
Classifier: Programming Language :: Python :: 3.7
Classifier: Programming Language :: Python :: 3.8
Classifier: Programming Language :: Python :: 3.9
Classifier: Programming Language :: Python :: 3.10
Classifier: Programming Language :: Python :: 3.11
Classifier: Programming Language :: Python :: 3.12
Requires-Python: >=3.7
License-File: LICENSE.txt
Requires-Dist: requests ==2.32.3
